pyproject.toml
setup.cfg
src/ta_cch_axcess/__init__.py
src/ta_cch_axcess/cch.py
src/ta_cch_axcess/cch_error.py
src/ta_cch_axcess/default_config.py
src/ta_cch_axcess/window_names.py
src/ta_cch_axcess.egg-info/PKG-INFO
src/ta_cch_axcess.egg-info/SOURCES.txt
src/ta_cch_axcess.egg-info/dependency_links.txt
src/ta_cch_axcess.egg-info/requires.txt
src/ta_cch_axcess.egg-info/top_level.txt
src/ta_cch_axcess/dialogs/__init__.py
src/ta_cch_axcess/dialogs/cch_dialog.py
src/ta_cch_axcess/dialogs/dashboard.py
src/ta_cch_axcess/dialogs/documents.py
src/ta_cch_axcess/dialogs/files_pending.py
src/ta_cch_axcess/dialogs/return_manager.py
src/ta_cch_axcess/dialogs/tax_return.py
src/ta_cch_axcess/meta_dialogs/__init__.py
src/ta_cch_axcess/meta_dialogs/electronic_filing_status.py