Metadata-Version: 2.1
Name: ta-cch-axcess
Version: 0.0.13
Summary: A pywinauto wrapper for CCH AXCESS
Home-page: https://www.thoughtfulautomation.com/
Author: Jacob Brooks
Author-email: jacob.brooks@thoughtfulautomation.com
Classifier: Programming Language :: Python :: 3
Classifier: Operating System :: OS Independent
Requires-Python: >=3.6
